zsim/__init__.py
zsim/cli.py
zsim/machine.py
zsim/zcode_parser.py
zsim/zcode_statement_parser.py
zsim/zcode_tokenizer.py
zsim/instruction_sets/__init__.py
zsim/instruction_sets/instruction_set.py
zsim/instruction_sets/z_instructions.py
zsim/instruction_sets/zds_instructions.py
zsim/instruction_sets/zfp_instructions.py
zsim/instruction_sets/zfpds_instructions.py
zsim/instructions/__init__.py
zsim/instructions/call_instruction.py
zsim/instructions/instruction.py
zsim/instructions/jump_instruction.py
zsim/parser/__init__.py
zsim/parser/parse_exception.py
zsim/parser/recursive_descent.py
zsim/parser/token.py
zsim/parser/token_type.py
zsim/parser/tokenizer.py
zsim_cli-0.6.1.dist-info/LICENSE
zsim_cli-0.6.1.dist-info/METADATA
zsim_cli-0.6.1.dist-info/WHEEL
zsim_cli-0.6.1.dist-info/entry_points.txt
zsim_cli-0.6.1.dist-info/top_level.txt
zsim_cli-0.6.1.dist-info/RECORD
