Metadata-Version: 2.1
Name: zsim-cli
Version: 0.6.1
Summary: A simulator for an assembly like toy-language.
Home-page: https://gitlab.com/justin_lehnen/zsim-cli
Author: Justin Lehnen
Author-email: justin.lehnen@gmx.de
License: UNKNOWN
Project-URL: Bug Tracker, https://gitlab.com/justin_lehnen/zsim-cli/issues
Platform: UNKNOWN
Classifier: Programming Language :: Python :: 3
Classifier: License :: OSI Approved :: The Unlicense (Unlicense)
Classifier: Operating System :: OS Independent
Requires-Python: >=3.6
License-File: LICENSE
Requires-Dist: click (>=5.1)
Requires-Dist: pytest
